setup.py
rhoCentralFlux/__init__.py
rhoCentralFlux.egg-info/PKG-INFO
rhoCentralFlux.egg-info/SOURCES.txt
rhoCentralFlux.egg-info/dependency_links.txt
rhoCentralFlux.egg-info/entry_points.txt
rhoCentralFlux.egg-info/requires.txt
rhoCentralFlux.egg-info/top_level.txt
rhoCentralFlux.egg-info/zip-safe
rhoCentralFlux/r1_6/__init__.py
rhoCentralFlux/r1_6/BCs/__init__.py
rhoCentralFlux/r1_6/BCs/rho/__init__.py
rhoCentralFlux/r1_7_0/__init__.py
rhoCentralFlux/r1_7_0/BCs/__init__.py
rhoCentralFlux/r1_7_0/BCs/rho/__init__.py
rhoCentralFlux/r2_0_0/__init__.py
rhoCentralFlux/r2_0_0/BCs/__init__.py
rhoCentralFlux/r2_0_0/BCs/rho/__init__.py
rhoCentralFlux/r2_1_0/__init__.py
rhoCentralFlux/r2_1_0/BCs/__init__.py
rhoCentralFlux/r2_1_0/BCs/rho/__init__.py
rhoCentralFlux/r2_1_1/__init__.py
rhoCentralFlux/r2_1_1/BCs/__init__.py
rhoCentralFlux/r2_1_1/BCs/rho/__init__.py